clldappconfig/__init__.py
clldappconfig/__main__.py
clldappconfig/cdstar.py
clldappconfig/config.py
clldappconfig/helpers.py
clldappconfig/util.py
clldappconfig/commands/__init__.py
clldappconfig/commands/ls.py
clldappconfig/commands/test_error.py
clldappconfig/tasks/__init__.py
clldappconfig/tasks/deployment.py
clldappconfig/tasks/letsencrypt.py
clldappconfig/tasks/other.py
clldappconfig/templates/503.html
clldappconfig/templates/__init__.py
clldappconfig/templates/config.ini
clldappconfig/templates/logrotate.conf
clldappconfig/templates/nginx-app.conf
clldappconfig/templates/nginx-default.conf
clldappconfig/templates/supervisor.conf
clldappconfig/templates/unaccent.rules
clldappconfig-1.2.0.dist-info/LICENSE
clldappconfig-1.2.0.dist-info/METADATA
clldappconfig-1.2.0.dist-info/WHEEL
clldappconfig-1.2.0.dist-info/entry_points.txt
clldappconfig-1.2.0.dist-info/top_level.txt
clldappconfig-1.2.0.dist-info/RECORD
